dellin/__init__.py
dellin/api.py
dellin/py.typed
dellin-0.1.0.dist-info/licenses/LICENSE
dellin-0.1.0.dist-info/METADATA
dellin-0.1.0.dist-info/WHEEL
dellin-0.1.0.dist-info/top_level.txt
dellin-0.1.0.dist-info/RECORD
